coordination_metrics_toolbox/__init__.py
coordination_metrics_toolbox/metrics.py
coordination_metrics_toolbox/utils.py
CoordinationMetricsToolbox-0.1.3.dist-info/METADATA
CoordinationMetricsToolbox-0.1.3.dist-info/WHEEL
CoordinationMetricsToolbox-0.1.3.dist-info/entry_points.txt
CoordinationMetricsToolbox-0.1.3.dist-info/top_level.txt
CoordinationMetricsToolbox-0.1.3.dist-info/RECORD
