Metadata-Version: 2.1
Name: CoordinationMetricsToolbox
Version: 0.1.3
Summary: A toolbox for measuring and analyzing coordination metrics.
Home-page: https://github.com/oceanedbs/CoordinationMetricsToolbox
Author: Océane Dubois
Author-email: 
Classifier: Programming Language :: Python :: 3
Classifier: Operating System :: OS Independent
Requires-Python: >=3.6
Requires-Dist: numpy
Requires-Dist: pandas
Requires-Dist: matplotlib
Requires-Dist: seaborn
Requires-Dist: scikit-learn
